odoo/addons/stock_lot_condition/README.rst
odoo/addons/stock_lot_condition/__init__.py
odoo/addons/stock_lot_condition/__manifest__.py
odoo/addons/stock_lot_condition/demo/stock_lot_condition_demo.xml
odoo/addons/stock_lot_condition/i18n/es.po
odoo/addons/stock_lot_condition/i18n/it.po
odoo/addons/stock_lot_condition/i18n/stock_lot_condition.pot
odoo/addons/stock_lot_condition/models/__init__.py
odoo/addons/stock_lot_condition/models/stock_lot.py
odoo/addons/stock_lot_condition/models/stock_lot_condition.py
odoo/addons/stock_lot_condition/readme/CONTRIBUTORS.md
odoo/addons/stock_lot_condition/readme/DESCRIPTION.md
odoo/addons/stock_lot_condition/readme/USAGE.md
odoo/addons/stock_lot_condition/security/ir.model.access.csv
odoo/addons/stock_lot_condition/static/description/icon.png
odoo/addons/stock_lot_condition/static/description/index.html
odoo/addons/stock_lot_condition/views/stock_lot_condition_views.xml
odoo/addons/stock_lot_condition/views/stock_lot_views.xml
odoo_addon_stock_lot_condition-18.0.1.0.0.4.dist-info/METADATA
odoo_addon_stock_lot_condition-18.0.1.0.0.4.dist-info/WHEEL
odoo_addon_stock_lot_condition-18.0.1.0.0.4.dist-info/top_level.txt
odoo_addon_stock_lot_condition-18.0.1.0.0.4.dist-info/RECORD
